sqlpluspython/__init__.py
sqlpluspython/db_connection.py
sqlpluspython/testing/__init__.py
sqlpluspython/testing/test_integration_database.py
sqlpluspython/testing/test_unit_database-object_uploads.py
sqlpluspython/testing/test_unit_database.py
sqlpluspython/utils/generate_test_data.py
sqlpluspython/utils/lists.py
sqlpluspython/utils/paths.py
sqlpluspython-0.2.0.dist-info/METADATA
sqlpluspython-0.2.0.dist-info/WHEEL
sqlpluspython-0.2.0.dist-info/top_level.txt
sqlpluspython-0.2.0.dist-info/RECORD
