Metadata-Version: 2.4
Name: SQLplusPython
Version: 0.2.0
Summary: Utils for SQL+Python - reliably work with SQL in Python apps 
Author-email: D Hansen <vj3gt0o0l@mozmail.com>
License: MIT
Project-URL: Repository, https://github.com/dennisdeh/SQLplusPython
Keywords: sqlalchemy,mysql,pandas,database,orm
Classifier: Programming Language :: Python :: 3
Classifier: Programming Language :: Python :: 3.12
Classifier: License :: OSI Approved :: MIT License
Classifier: Operating System :: OS Independent
Requires-Python: >=3.12
Requires-Dist: numpy==2.3.4
Requires-Dist: pandas==2.3.3
Requires-Dist: SQLAlchemy==2.0.44
Requires-Dist: mysql-connector-python==9.4.0
Requires-Dist: python-dotenv==1.1.1
Requires-Dist: pytz==2025.2
Requires-Dist: scikit-learn==1.7.2
Requires-Dist: scipy==1.16.2
Requires-Dist: six==1.17.0
Requires-Dist: typing_extensions==4.15.0
Requires-Dist: tzdata==2025.2
Requires-Dist: joblib==1.5.2
Requires-Dist: threadpoolctl==3.6.0
Requires-Dist: python-dateutil==2.9.0.post0
Requires-Dist: greenlet==3.2.4
